delta_rest_client/__init__.py
delta_rest_client/delta_rest_client.py
delta_rest_client/version.py
delta_rest_client-1.0.13.dist-info/METADATA
delta_rest_client-1.0.13.dist-info/WHEEL
delta_rest_client-1.0.13.dist-info/top_level.txt
delta_rest_client-1.0.13.dist-info/RECORD
