Metadata-Version: 2.1
Name: delta_rest_client
Version: 1.0.13
Summary: Rest Client for Delta Exchange
Home-page: https://github.com/delta-exchange/python-rest-client
Author: Arbaaz
Author-email: me@arbaaz.io
License: UNKNOWN
Platform: UNKNOWN
Classifier: Programming Language :: Python :: 3
Classifier: License :: OSI Approved :: MIT License
Classifier: Operating System :: OS Independent
